ecowitt2mqtt/__init__.py
ecowitt2mqtt/__main__.py
ecowitt2mqtt/backports/__init__.py
ecowitt2mqtt/backports/enum.py
ecowitt2mqtt/config.py
ecowitt2mqtt/const.py
ecowitt2mqtt/core.py
ecowitt2mqtt/data.py
ecowitt2mqtt/errors.py
ecowitt2mqtt/helpers/__init__.py
ecowitt2mqtt/helpers/calculator/__init__.py
ecowitt2mqtt/helpers/calculator/battery.py
ecowitt2mqtt/helpers/calculator/heap.py
ecowitt2mqtt/helpers/calculator/humidity.py
ecowitt2mqtt/helpers/calculator/illuminance.py
ecowitt2mqtt/helpers/calculator/leak.py
ecowitt2mqtt/helpers/calculator/lightning.py
ecowitt2mqtt/helpers/calculator/pollution.py
ecowitt2mqtt/helpers/calculator/precipitation.py
ecowitt2mqtt/helpers/calculator/pressure.py
ecowitt2mqtt/helpers/calculator/rainstate.py
ecowitt2mqtt/helpers/calculator/temperature.py
ecowitt2mqtt/helpers/calculator/time.py
ecowitt2mqtt/helpers/calculator/uv.py
ecowitt2mqtt/helpers/calculator/wind.py
ecowitt2mqtt/helpers/device.py
ecowitt2mqtt/helpers/publisher/__init__.py
ecowitt2mqtt/helpers/publisher/factory.py
ecowitt2mqtt/helpers/publisher/mqtt/__init__.py
ecowitt2mqtt/helpers/publisher/mqtt/hass.py
ecowitt2mqtt/helpers/server.py
ecowitt2mqtt/helpers/typing.py
ecowitt2mqtt/runtime.py
ecowitt2mqtt/util/__init__.py
ecowitt2mqtt/util/dt.py
ecowitt2mqtt/util/meteo.py
ecowitt2mqtt/util/unit_conversion.py
ecowitt2mqtt-2026.1.0.dist-info/METADATA
ecowitt2mqtt-2026.1.0.dist-info/WHEEL
ecowitt2mqtt-2026.1.0.dist-info/entry_points.txt
ecowitt2mqtt-2026.1.0.dist-info/licenses/LICENSE
ecowitt2mqtt-2026.1.0.dist-info/RECORD
