Metadata-Version: 2.4
Name: ecowitt2mqtt
Version: 2026.1.0
Summary: A small web server to send data from Ecowitt devices to an MQTT Broker
License: MIT
License-File: LICENSE
Author: Aaron Bach
Author-email: bachya1208@gmail.com
Requires-Python: >=3.10,<4.0
Classifier: License :: OSI Approved :: MIT License
Classifier: Programming Language :: Python
Classifier: Programming Language :: Python :: 3
Classifier: Programming Language :: Python :: 3.10
Classifier: Programming Language :: Python :: 3.11
Classifier: Programming Language :: Python :: 3.12
Classifier: Programming Language :: Python :: 3.13
Classifier: Programming Language :: Python :: 3.14
Classifier: Programming Language :: Python :: Implementation :: CPython
Classifier: Programming Language :: Python :: Implementation :: PyPy
Requires-Dist: aiohttp (>=3.9.0b0)
Requires-Dist: aiomqtt (>=1,<3)
Requires-Dist: certifi (>=2023.7.22)
Requires-Dist: colorlog (>=6.6.0,<7.0.0)
Requires-Dist: fastapi (>=0.89.1,<0.116.0)
Requires-Dist: frozenlist (>=1.4.0,<2.0.0)
Requires-Dist: meteocalc (>=1.1.0,<2.0.0)
Requires-Dist: pydantic (>=2.5.3,<3.0.0)
Requires-Dist: python-multipart (>=0.0.5,<0.0.18)
Requires-Dist: rapidfuzz (>=2.13,<4.0)
Requires-Dist: ruamel.yaml (>=0.18.5)
Requires-Dist: ruamel.yaml.clib (>=0.2.8,<0.3.0)
Requires-Dist: urllib3 (>=1.26.18)
Requires-Dist: uvicorn (>=0.19.0)
Requires-Dist: uvloop (>=0.17,<0.22)
Requires-Dist: yarl (>=1.9.2)
Project-URL: Bug Tracker, https://github.com/bachya/ecowitt2mqtt/issues
Project-URL: Changelog, https://github.com/bachya/ecowitt2mqtt/releases
Project-URL: Repository, https://github.com/bachya/ecowitt2mqtt
